[
  {
    "id": 1,
    "image": "https://images.unsplash.com/photo-1512499617640-c2f999098c01?w=500",
    "title": "Chat Master",
    "companyName": "Hero Tech",
    "description": "Fast and secure messaging app.",
    "size": 45,
    "reviews": 120000,
    "ratingAvg": 4.5,
    "downloads": 9000000
  },
  {
    "id": 2,
    "image": "https://images.unsplash.com/photo-1551650975-87deedd944c3?w=500",
    "title": "Photo Editor Pro",
    "companyName": "PixelLab",
    "description": "Edit photos like a pro.",
    "size": 60,
    "reviews": 95000,
    "ratingAvg": 4.6,
    "downloads": 8500000
  },
  {
    "id": 3,
    "image": "https://images.unsplash.com/photo-1517836357463-d25dfeac3438?w=500",
    "title": "Fitness Tracker",
    "companyName": "FitLife",
    "description": "Track your daily fitness.",
    "size": 35,
    "reviews": 80000,
    "ratingAvg": 4.3,
    "downloads": 7000000
  },
  {
    "id": 4,
    "image": "https://images.unsplash.com/photo-1511376777868-611b54f68947?w=500",
    "title": "Music Player X",
    "companyName": "SoundWave",
    "description": "Enjoy music anywhere.",
    "size": 50,
    "reviews": 110000,
    "ratingAvg": 4.7,
    "downloads": 10000000
  },
  {
    "id": 5,
    "image": "https://images.unsplash.com/photo-1504384308090-c894fdcc538d?w=500",
    "title": "Weather Now",
    "companyName": "SkyTech",
    "description": "Accurate weather forecast.",
    "size": 25,
    "reviews": 60000,
    "ratingAvg": 4.2,
    "downloads": 5000000
  },
  {
    "id": 6,
    "image": "https://images.unsplash.com/photo-1498050108023-c5249f4df085?w=500",
    "title": "Note Keeper",
    "companyName": "Hero Labs",
    "description": "Save your notes easily.",
    "size": 30,
    "reviews": 50000,
    "ratingAvg": 4.1,
    "downloads": 4000000
  },
  {
    "id": 7,
    "image": "https://images.unsplash.com/photo-1521737604893-d14cc237f11d?w=500",
    "title": "Task Manager",
    "companyName": "Hero Labs",
    "description": "Manage your daily tasks.",
    "size": 32,
    "reviews": 52000,
    "ratingAvg": 4.2,
    "downloads": 4500000
  },
  {
    "id": 8,
    "image": "https://images.unsplash.com/photo-1522202176988-66273c2fd55f?w=500",
    "title": "Video Maker",
    "companyName": "Hero Labs",
    "description": "Create amazing videos.",
    "size": 55,
    "reviews": 70000,
    "ratingAvg": 4.4,
    "downloads": 6000000
  },
  {
    "id": 9,
    "image": "https://images.unsplash.com/photo-1581276879432-15a19d654956?w=500",
    "title": "QR Scanner",
    "companyName": "Hero Labs",
    "description": "Scan QR codes instantly.",
    "size": 20,
    "reviews": 45000,
    "ratingAvg": 4.3,
    "downloads": 3500000
  },
  {
    "id": 10,
    "image": "https://images.unsplash.com/photo-1518770660439-4636190af475?w=500",
    "title": "File Manager",
    "companyName": "Hero Labs",
    "description": "Manage your files easily.",
    "size": 28,
    "reviews": 48000,
    "ratingAvg": 4.2,
    "downloads": 3700000
  },
  {
    "id": 11,
    "image": "https://images.unsplash.com/photo-1523475496153-3d6ccf8b0d5d?w=500",
    "title": "Language Learn",
    "companyName": "Hero Labs",
    "description": "Learn new languages easily.",
    "size": 40,
    "reviews": 60000,
    "ratingAvg": 4.5,
    "downloads": 5000000
  },
  {
    "id": 12,
    "image": "https://images.unsplash.com/photo-1555774698-0b77e0d5fac6?w=500",
    "title": "Calendar Pro",
    "companyName": "Hero Labs",
    "description": "Organize your schedule.",
    "size": 22,
    "reviews": 42000,
    "ratingAvg": 4.1,
    "downloads": 3000000
  },
  {
    "id": 13,
    "image": "https://images.unsplash.com/photo-1571019613454-1cb2f99b2d8b?w=500",
    "title": "Workout Daily",
    "companyName": "FitLife",
    "description": "Daily workout routines.",
    "size": 38,
    "reviews": 75000,
    "ratingAvg": 4.4,
    "downloads": 6500000
  },
  {
    "id": 14,
    "image": "https://images.unsplash.com/photo-1511671782779-c97d3d27a1d4?w=500",
    "title": "Podcast Player",
    "companyName": "SoundWave",
    "description": "Listen to podcasts easily.",
    "size": 48,
    "reviews": 58000,
    "ratingAvg": 4.3,
    "downloads": 4200000
  },
  {
    "id": 15,
    "image": "https://images.unsplash.com/photo-1556740749-887f6717d7e4?w=500",
    "title": "Expense Tracker",
    "companyName": "FinTech",
    "description": "Track your daily expenses.",
    "size": 26,
    "reviews": 46000,
    "ratingAvg": 4.2,
    "downloads": 3500000
  },
  {
    "id": 16,
    "image": "https://images.unsplash.com/photo-1505740420928-5e560c06d30e?w=500",
    "title": "Music Beats",
    "companyName": "SoundWave",
    "description": "Feel the beat everywhere.",
    "size": 52,
    "reviews": 67000,
    "ratingAvg": 4.6,
    "downloads": 7200000
  },
  {
    "id": 17,
    "image": "https://images.unsplash.com/photo-1537432376769-00a3a0a7c9b5?w=500",
    "title": "Code Helper",
    "companyName": "DevTools",
    "description": "Coding assistant app.",
    "size": 34,
    "reviews": 39000,
    "ratingAvg": 4.3,
    "downloads": 2800000
  },
  {
    "id": 18,
    "image": "https://images.unsplash.com/photo-1461749280684-dccba630e2f6?w=500",
    "title": "Dev Notes",
    "companyName": "DevTools",
    "description": "Store your code notes.",
    "size": 29,
    "reviews": 31000,
    "ratingAvg": 4.2,
    "downloads": 2600000
  },
  {
    "id": 19,
    "image": "https://images.unsplash.com/photo-1518770660439-4636190af475?w=500",
    "title": "File Explorer",
    "companyName": "Hero Labs",
    "description": "Explore your files easily.",
    "size": 24,
    "reviews": 28000,
    "ratingAvg": 4.1,
    "downloads": 2200000
  },
  {
    "id": 20,
    "image": "https://images.unsplash.com/photo-1522202176988-66273c2fd55f?w=500",
    "title": "Video Studio",
    "companyName": "MediaLab",
    "description": "Create stunning videos.",
    "size": 60,
    "reviews": 80000,
    "ratingAvg": 4.5,
    "downloads": 8000000
  },

  {
    "id": 21,
    "image": "https://images.unsplash.com/photo-1492724441997-5dc865305da7?w=500",
    "title": "Photo Master",
    "companyName": "PixelLab",
    "description": "Advanced photo editing.",
    "size": 58,
    "reviews": 90000,
    "ratingAvg": 4.6,
    "downloads": 8800000
  },
  {
    "id": 22,
    "image": "https://images.unsplash.com/photo-1515378791036-0648a3ef77b2?w=500",
    "title": "Chat Pro",
    "companyName": "Hero Tech",
    "description": "Next-gen messaging app.",
    "size": 47,
    "reviews": 130000,
    "ratingAvg": 4.7,
    "downloads": 9500000
  },
  {
    "id": 23,
    "image": "https://images.unsplash.com/photo-1581276879432-15a19d654956?w=500",
    "title": "QR Code Pro",
    "companyName": "Hero Labs",
    "description": "Scan & generate QR codes.",
    "size": 21,
    "reviews": 42000,
    "ratingAvg": 4.3,
    "downloads": 3600000
  },
  {
    "id": 24,
    "image": "https://images.unsplash.com/photo-1512941937669-90a1b58e7e9c?w=500",
    "title": "Mobile Cleaner",
    "companyName": "CleanTech",
    "description": "Boost your phone speed.",
    "size": 19,
    "reviews": 50000,
    "ratingAvg": 4.2,
    "downloads": 4000000
  },
  {
    "id": 25,
    "image": "https://images.unsplash.com/photo-1555066931-4365d14bab8c?w=500",
    "title": "Code Editor",
    "companyName": "DevTools",
    "description": "Edit code on the go.",
    "size": 36,
    "reviews": 45000,
    "ratingAvg": 4.4,
    "downloads": 3200000
  },
  {
    "id": 26,
    "image": "https://images.unsplash.com/photo-1521737604893-d14cc237f11d?w=500",
    "title": "Team Manager",
    "companyName": "WorkFlow",
    "description": "Manage your team tasks.",
    "size": 33,
    "reviews": 47000,
    "ratingAvg": 4.3,
    "downloads": 3800000
  },
  {
    "id": 27,
    "image": "https://images.unsplash.com/photo-1504384308090-c894fdcc538d?w=500",
    "title": "Weather Pro",
    "companyName": "SkyTech",
    "description": "Detailed weather updates.",
    "size": 27,
    "reviews": 52000,
    "ratingAvg": 4.5,
    "downloads": 4200000
  },
  {
    "id": 28,
    "image": "https://images.unsplash.com/photo-1517836357463-d25dfeac3438?w=500",
    "title": "Gym Trainer",
    "companyName": "FitLife",
    "description": "Your personal trainer.",
    "size": 42,
    "reviews": 78000,
    "ratingAvg": 4.6,
    "downloads": 6700000
  },
  {
    "id": 29,
    "image": "https://images.unsplash.com/photo-1505740420928-5e560c06d30e?w=500",
    "title": "Audio Mixer",
    "companyName": "SoundWave",
    "description": "Mix your own music.",
    "size": 55,
    "reviews": 62000,
    "ratingAvg": 4.4,
    "downloads": 5500000
  },
  {
    "id": 30,
    "image": "https://images.unsplash.com/photo-1558611848-73f7eb4001a1?w=500",
    "title": "Health Monitor",
    "companyName": "FitLife",
    "description": "Track your health stats.",
    "size": 37,
    "reviews": 69000,
    "ratingAvg": 4.5,
    "downloads": 6000000
  }
]